wDRMetrics/__init__.py
wDRMetrics/run.py
wDRMetrics/static/X_Z_Xr.zip
wDRMetrics/static/bootstrap.css
wDRMetrics/static/bootstrap.js
wDRMetrics/static/cancer.csv
wDRMetrics/static/digits.csv
wDRMetrics/static/jquery-3.3.1.min.js
wDRMetrics/static/jquery.blockUI.js
wDRMetrics/static/jquery.form.min.js
wDRMetrics/static/raman.csv
wDRMetrics/static/raman_xr.csv
wDRMetrics/static/raman_z.csv
wDRMetrics/templates/dr.html
wDRMetrics/templates/drx.html
wDRMetrics-0.0.4.dist-info/LICENCE
wDRMetrics-0.0.4.dist-info/METADATA
wDRMetrics-0.0.4.dist-info/WHEEL
wDRMetrics-0.0.4.dist-info/top_level.txt
wDRMetrics-0.0.4.dist-info/RECORD
